near_jsonrpc_client/__init__.py
near_jsonrpc_client/api_methods_async.py
near_jsonrpc_client/api_methods_sync.py
near_jsonrpc_client/base_client.py
near_jsonrpc_client/client.py
near_jsonrpc_client/errors.py
near_jsonrpc_client/transport.py
near_jsonrpc_client-1.0.26.dist-info/licenses/LICENSE
near_jsonrpc_models/__init__.py
near_jsonrpc_models/access_key.py
near_jsonrpc_models/access_key_creation_config_view.py
near_jsonrpc_models/access_key_info_view.py
near_jsonrpc_models/access_key_list.py
near_jsonrpc_models/access_key_permission.py
near_jsonrpc_models/access_key_permission_view.py
near_jsonrpc_models/access_key_view.py
near_jsonrpc_models/account_creation_config_view.py
near_jsonrpc_models/account_data_view.py
near_jsonrpc_models/account_id.py
near_jsonrpc_models/account_id_validity_rules_version.py
near_jsonrpc_models/account_info.py
near_jsonrpc_models/account_view.py
near_jsonrpc_models/account_with_public_key.py
near_jsonrpc_models/action_creation_config_view.py
near_jsonrpc_models/action_error.py
near_jsonrpc_models/action_error_kind.py
near_jsonrpc_models/action_view.py
near_jsonrpc_models/actions_validation_error.py
near_jsonrpc_models/add_gas_key_action.py
near_jsonrpc_models/add_key_action.py
near_jsonrpc_models/bandwidth_request.py
near_jsonrpc_models/bandwidth_request_bitmap.py
near_jsonrpc_models/bandwidth_requests.py
near_jsonrpc_models/bandwidth_requests_v1.py
near_jsonrpc_models/block_header_inner_lite_view.py
near_jsonrpc_models/block_header_view.py
near_jsonrpc_models/block_id.py
near_jsonrpc_models/block_reference.py
near_jsonrpc_models/block_status_view.py
near_jsonrpc_models/call_result.py
near_jsonrpc_models/catchup_status_view.py
near_jsonrpc_models/chunk_distribution_network_config.py
near_jsonrpc_models/chunk_distribution_uris.py
near_jsonrpc_models/chunk_hash.py
near_jsonrpc_models/chunk_header_view.py
near_jsonrpc_models/cloud_archival_writer_config.py
near_jsonrpc_models/compilation_error.py
near_jsonrpc_models/congestion_control_config_view.py
near_jsonrpc_client-1.0.26.dist-info/METADATA
near_jsonrpc_client-1.0.26.dist-info/WHEEL
near_jsonrpc_client-1.0.26.dist-info/top_level.txt
near_jsonrpc_client-1.0.26.dist-info/RECORD
