Metadata-Version: 2.4
Name: near-jsonrpc-client
Version: 1.0.26
Summary: A typed Python client for the NEAR JSON-RPC API with Pydantic models and async HTTP support
Requires-Python: >=3.9
License-File: LICENSE
Requires-Dist: httpx
Requires-Dist: pydantic>=2
Dynamic: license-file
Dynamic: requires-python
